README.rst
flameprof.py
setup.py
bin/flameprof
flameprof.egg-info/PKG-INFO
flameprof.egg-info/SOURCES.txt
flameprof.egg-info/dependency_links.txt
flameprof.egg-info/not-zip-safe
flameprof.egg-info/top_level.txt